{
    "Quotation": [
      {
        "order no": 1,
        "GardeningAddress": "Landscape Design",
        "GardeningArea": "https",
        "GardenImages":"",
        "Work Description": "Dolor sit amet dolor gravida placerat liberolorem ipsum dolor consectetur adipiscing elit, sed do eiusmod."
      },
      {
        "order no": 2,
        "GardeningAddress": "Landscape Design",
        "GardeningArea": "httpnnjjj",
        "GardenImages":"",
        "WorkDescription": "Dolor sit amet dolor gravida placerat liberolorem ipsum dolor consectetur adipiscing elit, sed do eiusmod."
        
      }
     
     
    ]
  }
  
  
  
  